{
  "aor": 0.0004546192893401016,
  "aqi": 0.009409309543147207,
  "bids_meta": {
    "EchoTime": 0.03,
    "EffectiveEchoSpacing": 0.000572,
    "PhaseEncodingDirection": "j-",
    "RepetitionTime": 0.68,
    "SliceTiming": [
      0.0,
      0.34,
      0.085,
      0.425,
      0.17,
      0.51,
      0.255,
      0.595,
      0.0,
      0.34,
      0.085,
      0.425,
      0.17,
      0.51,
      0.255,
      0.595,
      0.0,
      0.34,
      0.085,
      0.425,
      0.17,
      0.51,
      0.255,
      0.595,
      0.0,
      0.34,
      0.085,
      0.425,
      0.17,
      0.51,
      0.255,
      0.595,
      0.0,
      0.34,
      0.085,
      0.425,
      0.17,
      0.51,
      0.255,
      0.595,
      0.0,
      0.34,
      0.085,
      0.425,
      0.17,
      0.51,
      0.255,
      0.595,
      0.0,
      0.34,
      0.085,
      0.425,
      0.17,
      0.51,
      0.255,
      0.595,
      0.0,
      0.34,
      0.085,
      0.425,
      0.17,
      0.51,
      0.255,
      0.595
    ],
    "TaskName": "reward",
    "TotalReadoutTime": 0.0566,
    "dataset": "ds002316",
    "modality": "bold",
    "run_id": 1,
    "subject_id": "162",
    "task_id": "reward"
  },
  "dummy_trs": 1,
  "dvars_nstd": 32.84814772213559,
  "dvars_std": 1.020954037525425,
  "dvars_vstd": 0.9708652251355928,
  "efc": 0.47616154038019004,
  "fber": 8842.87109375,
  "fd_mean": 0.1324866741091725,
  "fd_num": 77,
  "fd_perc": 13.028764805414552,
  "fwhm_avg": 2.8984573057171397,
  "fwhm_x": 2.6991632853469043,
  "fwhm_y": 3.0371314232135136,
  "fwhm_z": 2.9590772085910015,
  "gcor": 0.0128607,
  "gsr_x": 0.0034199750516563654,
  "gsr_y": 0.016745829954743385,
  "provenance": {
    "md5sum": "ec23956edee00b4540fa53f6d5c76ae3",
    "settings": {
      "fd_thres": 0.2,
      "testing": false
    },
    "software": "mriqc",
    "version": "22.0.6",
    "webapi_port": null,
    "webapi_url": "https://mriqc.nimh.nih.gov/api/v1"
  },
  "size_t": 591,
  "size_x": 100,
  "size_y": 100,
  "size_z": 64,
  "snr": 3.4110285055433747,
  "spacing_tr": 0.6800000071525574,
  "spacing_x": 2.200000286102295,
  "spacing_y": 2.200000286102295,
  "spacing_z": 2.200000047683716,
  "summary_bg_k": 62.96153633384317,
  "summary_bg_mad": 52.14211342715964,
  "summary_bg_mean": 200.40908813476562,
  "summary_bg_median": 46.339630126953125,
  "summary_bg_n": 436637.0,
  "summary_bg_p05": 7.433409118652344,
  "summary_bg_p95": 958.3963134765617,
  "summary_bg_stdv": 440.09942626953125,
  "summary_fg_k": 0.9025020195006932,
  "summary_fg_mad": 1157.4077556283153,
  "summary_fg_mean": 4592.10009765625,
  "summary_fg_median": 4389.1640625,
  "summary_fg_n": 118289.0,
  "summary_fg_p05": 2868.5607421875,
  "summary_fg_p95": 6974.766210937499,
  "summary_fg_stdv": 1286.7513427734375,
  "tsnr": 33.978973388671875
}