{
  "aor": 0.0004909305993690852,
  "aqi": 0.009459168659305994,
  "bids_meta": {
    "EchoTime": 0.03,
    "EffectiveEchoSpacing": 0.000572,
    "PhaseEncodingDirection": "j-",
    "RepetitionTime": 0.68,
    "SliceTiming": [
      0.0,
      0.34,
      0.085,
      0.425,
      0.17,
      0.51,
      0.255,
      0.595,
      0.0,
      0.34,
      0.085,
      0.425,
      0.17,
      0.51,
      0.255,
      0.595,
      0.0,
      0.34,
      0.085,
      0.425,
      0.17,
      0.51,
      0.255,
      0.595,
      0.0,
      0.34,
      0.085,
      0.425,
      0.17,
      0.51,
      0.255,
      0.595,
      0.0,
      0.34,
      0.085,
      0.425,
      0.17,
      0.51,
      0.255,
      0.595,
      0.0,
      0.34,
      0.085,
      0.425,
      0.17,
      0.51,
      0.255,
      0.595,
      0.0,
      0.34,
      0.085,
      0.425,
      0.17,
      0.51,
      0.255,
      0.595,
      0.0,
      0.34,
      0.085,
      0.425,
      0.17,
      0.51,
      0.255,
      0.595
    ],
    "TaskName": "Beast",
    "TotalReadoutTime": 0.0566,
    "dataset": "ds002316",
    "modality": "bold",
    "run_id": 3,
    "subject_id": "317",
    "task_id": "Beast"
  },
  "dummy_trs": 0,
  "dvars_nstd": 42.18263251864141,
  "dvars_std": 1.0422415175355453,
  "dvars_vstd": 1.000095060679306,
  "efc": 0.5028501076790983,
  "fber": 4131.640625,
  "fd_mean": 0.10913242428025938,
  "fd_num": 45,
  "fd_perc": 7.097791798107256,
  "fwhm_avg": 3.0095787226479254,
  "fwhm_x": 2.752472667614489,
  "fwhm_y": 3.2959772012888906,
  "fwhm_z": 2.9802862990403978,
  "gcor": 0.00821735,
  "gsr_x": -0.002582827117294073,
  "gsr_y": 0.06440120190382004,
  "provenance": {
    "md5sum": "a4463866357a3845d4b052c520d7e51f",
    "settings": {
      "fd_thres": 0.2,
      "testing": false
    },
    "software": "mriqc",
    "version": "22.0.6",
    "webapi_port": null,
    "webapi_url": "https://mriqc.nimh.nih.gov/api/v1"
  },
  "size_t": 634,
  "size_x": 100,
  "size_y": 100,
  "size_z": 64,
  "snr": 3.0479682313346848,
  "spacing_tr": 0.6800000071525574,
  "spacing_x": 2.200000047683716,
  "spacing_y": 2.200000047683716,
  "spacing_z": 2.200000047683716,
  "summary_bg_k": 23.082479663027684,
  "summary_bg_mad": 165.66396661840128,
  "summary_bg_mean": 636.66748046875,
  "summary_bg_median": 151.97842407226562,
  "summary_bg_n": 425788.0,
  "summary_bg_p05": 27.320806884765624,
  "summary_bg_p95": 3286.7440185546843,
  "summary_bg_stdv": 1375.0924072265625,
  "summary_fg_k": 0.6283064076440934,
  "summary_fg_mad": 3080.1223972998396,
  "summary_fg_mean": 10401.7021484375,
  "summary_fg_median": 9951.8046875,
  "summary_fg_n": 125700.0,
  "summary_fg_p05": 5848.086840820312,
  "summary_fg_p95": 16253.799999999997,
  "summary_fg_stdv": 3265.048828125,
  "tsnr": 28.88912582397461
}